{
  "sections": {
    "esp8266": {
      "key": "esp8266",
      "title": "ESP8266 (ESP8266EX)",
      "notes": [
        "ESP8266: GPIO0, GPIO2, and GPIO15 are strapping pins; use them only if the external circuit preserves the required boot level.",
        "GPIO6-11 are normally reserved for the external SPI flash interface and should not be used as GPIO.",
        "GPIO4, GPIO5, GPIO12, GPIO13, and GPIO14 are general-purpose pins with no boot strap restrictions.",
        "UART0 (GPIO1 TX, GPIO3 RX) is used for programming and logs. Reusing these pins can disrupt flashing or serial communication.",
        "GPIO16 is a special RTC/deep-sleep wake pin with limited GPIO features; A0/ADC0 is analog-input-only."
      ],
      "rows": [
        {
          "id": "GPIO0",
          "input": "Yes (internal pull-up)",
          "output": "Yes",
          "status": "caution",
          "value": "0",
          "selectable": true,
          "warning": "Strapping (BOOT0) - must be HIGH at boot (LOW forces flash mode). After boot it can be used as a normal input. ESPHome warns about strapping pins."
        },
        {
          "id": "GPIO1",
          "input": "Yes (RX0)",
          "output": "Yes (UART0 TX)",
          "status": "caution",
          "value": "1",
          "selectable": true,
          "warning": "UART0 TX outputs boot logs. Default state is HIGH at boot; boot can fail if forced LOW. Avoid attaching devices that react to boot pulses."
        },
        {
          "id": "GPIO2",
          "input": "Yes (internal pull-up)",
          "output": "Yes",
          "status": "caution",
          "value": "2",
          "selectable": true,
          "warning": "Strapping - must be HIGH at boot; LOW prevents boot. Often connected to on-board LED. ESPHome warns about strapping pins."
        },
        {
          "id": "GPIO3",
          "input": "Yes (UART0 RX)",
          "output": "Yes*",
          "status": "caution",
          "value": "3",
          "selectable": true,
          "warning": "UART0 RX is used for serial communication. Pull-up at boot. It can be driven as an output in software*, but this is nonstandard; keep for serial/programming."
        },
        {
          "id": "GPIO4",
          "input": "Yes",
          "output": "Yes",
          "status": "safe",
          "value": "4",
          "selectable": true,
          "note": "General-purpose GPIO. No boot restrictions. Safe for relays and peripherals."
        },
        {
          "id": "GPIO5",
          "input": "Yes",
          "output": "Yes",
          "status": "safe",
          "value": "5",
          "selectable": true,
          "note": "General-purpose GPIO. Often used as I2C SCL. Safe at boot."
        },
        {
          "id": "GPIO6",
          "input": "No",
          "output": "No",
          "status": "avoid",
          "value": "6",
          "selectable": true,
          "error": "Reserved (Flash) - connected to external SPI flash. Do not use as GPIO. ESPHome blocks these pins."
        },
        {
          "id": "GPIO7",
          "input": "No",
          "output": "No",
          "status": "avoid",
          "value": "7",
          "selectable": true,
          "error": "Reserved (Flash) - connected to external SPI flash. Do not use as GPIO. ESPHome blocks these pins."
        },
        {
          "id": "GPIO8",
          "input": "No",
          "output": "No",
          "status": "avoid",
          "value": "8",
          "selectable": true,
          "error": "Reserved (Flash) - connected to external SPI flash. Do not use as GPIO. ESPHome blocks these pins."
        },
        {
          "id": "GPIO9",
          "input": "No",
          "output": "No",
          "status": "avoid",
          "value": "9",
          "selectable": true,
          "error": "Reserved (Flash) - connected to external SPI flash. Do not use as GPIO. ESPHome blocks these pins."
        },
        {
          "id": "GPIO10",
          "input": "No",
          "output": "No",
          "status": "avoid",
          "value": "10",
          "selectable": true,
          "error": "Reserved (Flash) - connected to external SPI flash. Do not use as GPIO. ESPHome blocks these pins."
        },
        {
          "id": "GPIO11",
          "input": "No",
          "output": "No",
          "status": "avoid",
          "value": "11",
          "selectable": true,
          "error": "Reserved (Flash) - connected to external SPI flash. Do not use as GPIO. ESPHome blocks these pins."
        },
        {
          "id": "GPIO12",
          "input": "Yes",
          "output": "Yes",
          "status": "safe",
          "value": "12",
          "selectable": true,
          "note": "General-purpose GPIO. Often SPI MISO. No boot restrictions."
        },
        {
          "id": "GPIO13",
          "input": "Yes",
          "output": "Yes",
          "status": "safe",
          "value": "13",
          "selectable": true,
          "note": "General-purpose GPIO. Often SPI MOSI. No boot restrictions."
        },
        {
          "id": "GPIO14",
          "input": "Yes",
          "output": "Yes",
          "status": "safe",
          "value": "14",
          "selectable": true,
          "note": "General-purpose GPIO. Often SPI SCLK. Generates a short PWM pulse at reset."
        },
        {
          "id": "GPIO15",
          "input": "Yes (internal pull-down)",
          "output": "Yes",
          "status": "caution",
          "value": "15",
          "selectable": true,
          "warning": "Strapping - must be LOW at boot. Often used as SPI CS. ESPHome warns about strapping pins."
        },
        {
          "id": "GPIO16",
          "input": "No (no interrupts)",
          "output": "Yes (no PWM/I2C)",
          "status": "caution",
          "value": "16",
          "selectable": true,
          "warning": "Special GPIO16 (D0). No interrupts, PWM, or I2C. Default HIGH at boot. Used for deep sleep wake (connects to RESET)."
        },
        {
          "id": "A0 (ADC0)",
          "input": "Analog in",
          "output": "-",
          "status": "caution",
          "value": "A0",
          "selectable": true,
          "warning": "Analog input only. 0-1V on bare chip, up to 3.3V on modules with divider."
        }
      ]
    },
    "esp32": {
      "key": "esp32",
      "title": "ESP32 (original ESP32, WROOM-32)",
      "notes": [
        "ESP32: GPIO0, GPIO2, GPIO5, GPIO12, and GPIO15 are strapping pins sampled during reset; external circuitry must not force an invalid boot level.",
        "GPIO6-11 are normally connected to SPI flash and should not be used. On modules with PSRAM, GPIO16-17 can also be unavailable; verify the exact module.",
        "GPIO34-39 are input-only and do not have software-enabled internal pull-up/pull-down resistors.",
        "GPIO1 (TXD0) and GPIO3 (RXD0) are used for UART0 programming/logs. Reuse is possible, but attached circuitry must tolerate boot logs and flashing.",
        "I2C and SPI signals can usually be remapped through the GPIO matrix; default peripheral labels alone are not a reason to mark a pin as caution."
      ],
      "rows": [
        {
          "id": "GPIO0",
          "input": "Yes (internal pull-up)",
          "output": "Yes",
          "status": "caution",
          "value": "0",
          "selectable": true,
          "warning": "Strapping - GPIO0 selects boot mode. Must be HIGH at boot (LOW forces flash). ESPHome warns about strapping pins."
        },
        {
          "id": "GPIO1",
          "input": "Yes*",
          "output": "Yes (UART0 TX)",
          "status": "caution",
          "value": "1",
          "selectable": true,
          "warning": "UART0 TX outputs boot logs (default HIGH at boot). If forced LOW during reset, boot can fail. Avoid devices that pull it down."
        },
        {
          "id": "GPIO2",
          "input": "Yes",
          "output": "Yes",
          "status": "caution",
          "value": "2",
          "selectable": true,
          "warning": "Strapping - must be LOW/FLOAT at boot. Pulling HIGH prevents boot. ESPHome warns about strapping pins."
        },
        {
          "id": "GPIO3",
          "input": "Yes (UART0 RX)",
          "output": "Yes*",
          "status": "caution",
          "value": "3",
          "selectable": true,
          "warning": "UART0 RX is used for programming/logs. Default pull-up at boot. Can be output in software*, but keep for UART0 when possible."
        },
        {
          "id": "GPIO4",
          "input": "Yes",
          "output": "Yes",
          "status": "safe",
          "value": "4",
          "selectable": true,
          "note": "General-purpose GPIO. No strapping function. Safe at boot. Supports ADC2_CH0 and touch T0."
        },
        {
          "id": "GPIO5",
          "input": "Yes",
          "output": "Yes",
          "status": "caution",
          "value": "5",
          "selectable": true,
          "warning": "Strapping - must be HIGH at boot. Emits PWM during reset. Default VSPI CS0. ESPHome warns about strapping pins."
        },
        {
          "id": "GPIO6",
          "input": "No",
          "output": "No",
          "status": "avoid",
          "value": "6",
          "selectable": true,
          "error": "Reserved (SPI Flash) - connected to internal flash. Do not use. ESPHome blocks these pins."
        },
        {
          "id": "GPIO7",
          "input": "No",
          "output": "No",
          "status": "avoid",
          "value": "7",
          "selectable": true,
          "error": "Reserved (SPI Flash) - connected to internal flash. Do not use. ESPHome blocks these pins."
        },
        {
          "id": "GPIO8",
          "input": "No",
          "output": "No",
          "status": "avoid",
          "value": "8",
          "selectable": true,
          "error": "Reserved (SPI Flash) - connected to internal flash. Do not use. ESPHome blocks these pins."
        },
        {
          "id": "GPIO9",
          "input": "No",
          "output": "No",
          "status": "avoid",
          "value": "9",
          "selectable": true,
          "error": "Reserved (SPI Flash) - connected to internal flash. Do not use. ESPHome blocks these pins."
        },
        {
          "id": "GPIO10",
          "input": "No",
          "output": "No",
          "status": "avoid",
          "value": "10",
          "selectable": true,
          "error": "Reserved (SPI Flash) - connected to internal flash. Do not use. ESPHome blocks these pins."
        },
        {
          "id": "GPIO11",
          "input": "No",
          "output": "No",
          "status": "avoid",
          "value": "11",
          "selectable": true,
          "error": "Reserved (SPI Flash) - connected to internal flash. Do not use. ESPHome blocks these pins."
        },
        {
          "id": "GPIO12",
          "input": "Yes",
          "output": "Yes",
          "status": "caution",
          "value": "12",
          "selectable": true,
          "warning": "Strapping - must be LOW at boot to keep flash at 3.3V. HIGH can force 1.8V and break boot. ESPHome warns about strapping pins."
        },
        {
          "id": "GPIO13",
          "input": "Yes",
          "output": "Yes",
          "status": "safe",
          "value": "13",
          "selectable": true,
          "note": "General-purpose GPIO (ADC2_CH4, Touch T4). No boot restrictions."
        },
        {
          "id": "GPIO14",
          "input": "Yes",
          "output": "Yes",
          "status": "safe",
          "value": "14",
          "selectable": true,
          "note": "General-purpose GPIO (ADC2_CH6, Touch T6). Emits PWM during reset."
        },
        {
          "id": "GPIO15",
          "input": "Yes",
          "output": "Yes",
          "status": "caution",
          "value": "15",
          "selectable": true,
          "warning": "Strapping - must be HIGH at boot. Emits PWM during reset. ESPHome warns about strapping pins."
        },
        {
          "id": "GPIO16",
          "input": "Yes",
          "output": "Yes",
          "status": "safe",
          "value": "16",
          "selectable": true,
          "note": "General-purpose GPIO (ADC2_CH8). UART2 RX on some boards."
        },
        {
          "id": "GPIO17",
          "input": "Yes",
          "output": "Yes",
          "status": "safe",
          "value": "17",
          "selectable": true,
          "note": "General-purpose GPIO (ADC2_CH9). UART2 TX on some boards."
        },
        {
          "id": "GPIO18",
          "input": "Yes",
          "output": "Yes",
          "status": "safe",
          "value": "18",
          "selectable": true,
          "note": "General-purpose GPIO. Default VSPI SCLK."
        },
        {
          "id": "GPIO19",
          "input": "Yes",
          "output": "Yes",
          "status": "safe",
          "value": "19",
          "selectable": true,
          "note": "General-purpose GPIO. Default VSPI MISO."
        },
        {
          "id": "GPIO21",
          "input": "Yes",
          "output": "Yes",
          "status": "safe",
          "value": "21",
          "selectable": true,
          "note": "General-purpose GPIO. Default I2C SDA on many dev kits."
        },
        {
          "id": "GPIO22",
          "input": "Yes",
          "output": "Yes",
          "status": "safe",
          "value": "22",
          "selectable": true,
          "note": "General-purpose GPIO. Default I2C SCL on many dev kits."
        },
        {
          "id": "GPIO23",
          "input": "Yes",
          "output": "Yes",
          "status": "safe",
          "value": "23",
          "selectable": true,
          "note": "General-purpose GPIO. Default VSPI MOSI."
        },
        {
          "id": "GPIO25",
          "input": "Yes",
          "output": "Yes",
          "status": "safe",
          "value": "25",
          "selectable": true,
          "note": "General-purpose GPIO with DAC1 output (ADC2_CH8)."
        },
        {
          "id": "GPIO26",
          "input": "Yes",
          "output": "Yes",
          "status": "safe",
          "value": "26",
          "selectable": true,
          "note": "General-purpose GPIO with DAC2 output (ADC2_CH9)."
        },
        {
          "id": "GPIO27",
          "input": "Yes",
          "output": "Yes",
          "status": "safe",
          "value": "27",
          "selectable": true,
          "note": "General-purpose GPIO (ADC2_CH7, Touch T7)."
        },
        {
          "id": "GPIO32",
          "input": "Yes",
          "output": "Yes",
          "status": "safe",
          "value": "32",
          "selectable": true,
          "note": "General-purpose GPIO (ADC1_CH4, Touch T9, RTC_GPIO9)."
        },
        {
          "id": "GPIO33",
          "input": "Yes",
          "output": "Yes",
          "status": "safe",
          "value": "33",
          "selectable": true,
          "note": "General-purpose GPIO (ADC1_CH5, Touch T8, RTC_GPIO8)."
        },
        {
          "id": "GPIO34",
          "input": "Yes",
          "output": "No",
          "status": "caution",
          "value": "34",
          "selectable": true,
          "warning": "Input-only GPIO34 (ADC1_CH6, RTC_GPIO4)."
        },
        {
          "id": "GPIO35",
          "input": "Yes",
          "output": "No",
          "status": "caution",
          "value": "35",
          "selectable": true,
          "warning": "Input-only GPIO35 (ADC1_CH7, RTC_GPIO5)."
        },
        {
          "id": "GPIO36",
          "input": "Yes",
          "output": "No",
          "status": "caution",
          "value": "36",
          "selectable": true,
          "warning": "Input-only GPIO36 (ADC1_CH0, RTC_GPIO0)."
        },
        {
          "id": "GPIO37",
          "input": "Yes",
          "output": "No",
          "status": "caution",
          "value": "37",
          "selectable": true,
          "warning": "Input-only GPIO37 (ADC1_CH1). Not broken out on some modules."
        },
        {
          "id": "GPIO38",
          "input": "Yes",
          "output": "No",
          "status": "caution",
          "value": "38",
          "selectable": true,
          "warning": "Input-only GPIO38 (ADC1_CH2). Not broken out on some modules."
        },
        {
          "id": "GPIO39",
          "input": "Yes",
          "output": "No",
          "status": "caution",
          "value": "39",
          "selectable": true,
          "warning": "Input-only GPIO39 (ADC1_CH3, RTC_GPIO3)."
        }
      ]
    },
    "esp32-s2": {
      "key": "esp32-s2",
      "title": "ESP32-S2 (ESP32-S2-SOLO)",
      "notes": [
        "ESP32-S2: GPIO0, GPIO45, and GPIO46 are strapping pins sampled during reset; external circuitry must preserve the required boot levels.",
        "GPIO46 is input-only and has a fixed pull-down. GPIO26-32 are usually used for SPI flash/PSRAM and are not recommended for GPIO.",
        "GPIO19 and GPIO20 are the native USB D-/D+ pins. Use them as GPIO only when native USB is not needed.",
        "GPIO39-42 are JTAG pins; they can be used as GPIO if JTAG debugging is not used.",
        "ADC, touch, RTC, I2C, and SPI alternate functions do not by themselves make a pin caution."
      ],
      "rows": [
        {
          "id": "GPIO0",
          "input": "Yes",
          "output": "Yes",
          "status": "caution",
          "value": "0",
          "selectable": true,
          "warning": "Strapping - selects boot mode. Must be HIGH at boot (LOW forces flash)."
        },
        {
          "id": "GPIO1",
          "input": "Yes",
          "output": "Yes",
          "status": "safe",
          "value": "1",
          "selectable": true,
          "note": "General-purpose GPIO (ADC1_CH5)."
        },
        {
          "id": "GPIO2",
          "input": "Yes",
          "output": "Yes",
          "status": "safe",
          "value": "2",
          "selectable": true,
          "note": "General-purpose GPIO (ADC1_CH6)."
        },
        {
          "id": "GPIO3",
          "input": "Yes",
          "output": "Yes",
          "status": "safe",
          "value": "3",
          "selectable": true,
          "note": "General-purpose GPIO (ADC1_CH7)."
        },
        {
          "id": "GPIO4",
          "input": "Yes",
          "output": "Yes",
          "status": "safe",
          "value": "4",
          "selectable": true,
          "note": "General-purpose GPIO (ADC1_CH4)."
        },
        {
          "id": "GPIO5",
          "input": "Yes",
          "output": "Yes",
          "status": "safe",
          "value": "5",
          "selectable": true,
          "note": "General-purpose GPIO (ADC2_CH5)."
        },
        {
          "id": "GPIO6",
          "input": "Yes",
          "output": "Yes",
          "status": "safe",
          "value": "6",
          "selectable": true,
          "note": "General-purpose GPIO (ADC2_CH6)."
        },
        {
          "id": "GPIO7",
          "input": "Yes",
          "output": "Yes",
          "status": "safe",
          "value": "7",
          "selectable": true,
          "note": "General-purpose GPIO (ADC2_CH7)."
        },
        {
          "id": "GPIO8",
          "input": "Yes",
          "output": "Yes",
          "status": "safe",
          "value": "8",
          "selectable": true,
          "note": "General-purpose GPIO (ADC2_CH8)."
        },
        {
          "id": "GPIO9",
          "input": "Yes",
          "output": "Yes",
          "status": "safe",
          "value": "9",
          "selectable": true,
          "note": "General-purpose GPIO (ADC2_CH9)."
        },
        {
          "id": "GPIO10",
          "input": "Yes",
          "output": "Yes",
          "status": "safe",
          "value": "10",
          "selectable": true,
          "note": "General-purpose GPIO (ADC1_CH8)."
        },
        {
          "id": "GPIO11",
          "input": "Yes",
          "output": "Yes",
          "status": "safe",
          "value": "11",
          "selectable": true,
          "note": "General-purpose GPIO (ADC1_CH9)."
        },
        {
          "id": "GPIO12",
          "input": "Yes",
          "output": "Yes",
          "status": "safe",
          "value": "12",
          "selectable": true,
          "note": "General-purpose GPIO (ADC2_CH0)."
        },
        {
          "id": "GPIO13",
          "input": "Yes",
          "output": "Yes",
          "status": "safe",
          "value": "13",
          "selectable": true,
          "note": "General-purpose GPIO (ADC2_CH1)."
        },
        {
          "id": "GPIO14",
          "input": "Yes",
          "output": "Yes",
          "status": "safe",
          "value": "14",
          "selectable": true,
          "note": "General-purpose GPIO (ADC2_CH2)."
        },
        {
          "id": "GPIO15",
          "input": "Yes",
          "output": "Yes",
          "status": "safe",
          "value": "15",
          "selectable": true,
          "note": "General-purpose GPIO (ADC2_CH3)."
        },
        {
          "id": "GPIO16",
          "input": "Yes",
          "output": "Yes",
          "status": "safe",
          "value": "16",
          "selectable": true,
          "note": "General-purpose GPIO (ADC2_CH4)."
        },
        {
          "id": "GPIO17",
          "input": "Yes",
          "output": "Yes",
          "status": "safe",
          "value": "17",
          "selectable": true,
          "note": "General-purpose GPIO."
        },
        {
          "id": "GPIO18",
          "input": "Yes",
          "output": "Yes",
          "status": "safe",
          "value": "18",
          "selectable": true,
          "note": "General-purpose GPIO. On DevKitC-1 controls built-in addressable RGB LED."
        },
        {
          "id": "GPIO19",
          "input": "Yes",
          "output": "Yes",
          "status": "caution",
          "value": "19",
          "selectable": true,
          "warning": "Native USB D- pin. Use as GPIO only when native USB is not required."
        },
        {
          "id": "GPIO20",
          "input": "Yes",
          "output": "Yes",
          "status": "caution",
          "value": "20",
          "selectable": true,
          "warning": "Native USB D+ pin. Use as GPIO only when native USB is not required."
        },
        {
          "id": "GPIO21",
          "input": "Yes",
          "output": "Yes",
          "status": "safe",
          "value": "21",
          "selectable": true,
          "note": "General-purpose GPIO."
        },
        {
          "id": "GPIO26",
          "input": "-",
          "output": "-",
          "status": "avoid",
          "value": "26",
          "selectable": true,
          "error": "Reserved (Flash) - GPIO26-32 connected to internal flash/PSRAM and not available."
        },
        {
          "id": "GPIO27",
          "input": "-",
          "output": "-",
          "status": "avoid",
          "value": "27",
          "selectable": true,
          "error": "Reserved (Flash)."
        },
        {
          "id": "GPIO28",
          "input": "-",
          "output": "-",
          "status": "avoid",
          "value": "28",
          "selectable": true,
          "error": "Reserved (Flash)."
        },
        {
          "id": "GPIO29",
          "input": "-",
          "output": "-",
          "status": "avoid",
          "value": "29",
          "selectable": true,
          "error": "Reserved (Flash)."
        },
        {
          "id": "GPIO30",
          "input": "-",
          "output": "-",
          "status": "avoid",
          "value": "30",
          "selectable": true,
          "error": "Reserved (Flash)."
        },
        {
          "id": "GPIO31",
          "input": "-",
          "output": "-",
          "status": "avoid",
          "value": "31",
          "selectable": true,
          "error": "Reserved (Flash)."
        },
        {
          "id": "GPIO32",
          "input": "-",
          "output": "-",
          "status": "avoid",
          "value": "32",
          "selectable": true,
          "error": "Reserved (Flash)."
        },
        {
          "id": "GPIO33",
          "input": "Yes",
          "output": "Yes",
          "status": "safe",
          "value": "33",
          "selectable": true,
          "note": "General-purpose GPIO."
        },
        {
          "id": "GPIO34",
          "input": "Yes",
          "output": "Yes",
          "status": "safe",
          "value": "34",
          "selectable": true,
          "note": "General-purpose GPIO."
        },
        {
          "id": "GPIO35",
          "input": "Yes",
          "output": "Yes",
          "status": "safe",
          "value": "35",
          "selectable": true,
          "note": "General-purpose GPIO."
        },
        {
          "id": "GPIO36",
          "input": "Yes",
          "output": "Yes",
          "status": "safe",
          "value": "36",
          "selectable": true,
          "note": "General-purpose GPIO."
        },
        {
          "id": "GPIO37",
          "input": "Yes",
          "output": "Yes",
          "status": "safe",
          "value": "37",
          "selectable": true,
          "note": "General-purpose GPIO."
        },
        {
          "id": "GPIO38",
          "input": "Yes",
          "output": "Yes",
          "status": "safe",
          "value": "38",
          "selectable": true,
          "note": "General-purpose GPIO."
        },
        {
          "id": "GPIO39",
          "input": "Yes",
          "output": "Yes",
          "status": "safe",
          "value": "39",
          "selectable": true,
          "note": "General-purpose GPIO. Also JTAG TCK; using it as GPIO prevents use of that JTAG signal."
        },
        {
          "id": "GPIO40",
          "input": "Yes",
          "output": "Yes",
          "status": "safe",
          "value": "40",
          "selectable": true,
          "note": "General-purpose GPIO. Also JTAG TMS; using it as GPIO prevents use of that JTAG signal."
        },
        {
          "id": "GPIO41",
          "input": "Yes",
          "output": "Yes",
          "status": "safe",
          "value": "41",
          "selectable": true,
          "note": "General-purpose GPIO. Also JTAG TDI; using it as GPIO prevents use of that JTAG signal."
        },
        {
          "id": "GPIO42",
          "input": "Yes",
          "output": "Yes",
          "status": "safe",
          "value": "42",
          "selectable": true,
          "note": "General-purpose GPIO. Also JTAG TDO; using it as GPIO prevents use of that JTAG signal."
        },
        {
          "id": "GPIO45",
          "input": "Yes",
          "output": "Yes",
          "status": "caution",
          "value": "45",
          "selectable": true,
          "warning": "Strapping - GPIO45 selects VDD_SDIO voltage. Ensure correct default state; invalid levels can break flash."
        },
        {
          "id": "GPIO46",
          "input": "Yes (input-only)",
          "output": "No",
          "status": "caution",
          "value": "46",
          "selectable": true,
          "warning": "Strapping and input-only GPIO46. Fixed pull-down; cannot be used as an output."
        }
      ]
    },
    "esp32-s3": {
      "key": "esp32-s3",
      "title": "ESP32-S3 (ESP32-S3-WROOM)",
      "notes": [
        "ESP32-S3: GPIO0, GPIO3, GPIO45, and GPIO46 are strapping pins sampled during reset; GPIO45 is especially sensitive because it affects VDD_SPI/flash-voltage selection.",
        "GPIO22-25 are not valid GPIO numbers on ESP32-S3. GPIO26-32 are usually used for SPI flash/PSRAM and are not recommended for GPIO.",
        "GPIO19 and GPIO20 are used by USB-Serial/JTAG by default; using them as GPIO disables that USB-JTAG function.",
        "GPIO33-37 may be connected to Octal flash/PSRAM on ESP32-S3R8/R8V-class modules, so verify the exact module before using them.",
        "GPIO43 and GPIO44 are UART0 pins used for flashing/logs on many boards. ADC/touch alternate functions alone are not a warning condition."
      ],
      "rows": [
        {
          "id": "GPIO0",
          "input": "Yes",
          "output": "Yes",
          "status": "caution",
          "value": "0",
          "selectable": true,
          "warning": "Strapping - selects boot mode. Pull-up; must be HIGH at boot."
        },
        {
          "id": "GPIO1",
          "input": "Yes",
          "output": "Yes",
          "status": "safe",
          "value": "1",
          "selectable": true,
          "note": "General-purpose GPIO (ADC1_CH0, Touch1)."
        },
        {
          "id": "GPIO2",
          "input": "Yes",
          "output": "Yes",
          "status": "safe",
          "value": "2",
          "selectable": true,
          "note": "General-purpose GPIO (ADC1_CH1, Touch2)."
        },
        {
          "id": "GPIO3",
          "input": "Yes",
          "output": "Yes",
          "status": "caution",
          "value": "3",
          "selectable": true,
          "warning": "Strapping - selects JTAG source. Keep default pull-down at boot."
        },
        {
          "id": "GPIO4",
          "input": "Yes",
          "output": "Yes",
          "status": "safe",
          "value": "4",
          "selectable": true,
          "note": "General-purpose GPIO (ADC1_CH3, Touch4)."
        },
        {
          "id": "GPIO5",
          "input": "Yes",
          "output": "Yes",
          "status": "safe",
          "value": "5",
          "selectable": true,
          "note": "General-purpose GPIO (ADC1_CH4, Touch5)."
        },
        {
          "id": "GPIO6",
          "input": "Yes",
          "output": "Yes",
          "status": "safe",
          "value": "6",
          "selectable": true,
          "note": "General-purpose GPIO (ADC1_CH5, Touch6)."
        },
        {
          "id": "GPIO7",
          "input": "Yes",
          "output": "Yes",
          "status": "safe",
          "value": "7",
          "selectable": true,
          "note": "General-purpose GPIO (ADC1_CH6, Touch7)."
        },
        {
          "id": "GPIO8",
          "input": "Yes",
          "output": "Yes",
          "status": "safe",
          "value": "8",
          "selectable": true,
          "note": "General-purpose GPIO (ADC1_CH7, Touch8)."
        },
        {
          "id": "GPIO9",
          "input": "Yes",
          "output": "Yes",
          "status": "safe",
          "value": "9",
          "selectable": true,
          "note": "General-purpose GPIO (ADC1_CH8, Touch9)."
        },
        {
          "id": "GPIO10",
          "input": "Yes",
          "output": "Yes",
          "status": "safe",
          "value": "10",
          "selectable": true,
          "note": "General-purpose GPIO (ADC2_CH0, Touch10)."
        },
        {
          "id": "GPIO11",
          "input": "Yes",
          "output": "Yes",
          "status": "safe",
          "value": "11",
          "selectable": true,
          "note": "General-purpose GPIO (ADC2_CH1, Touch11)."
        },
        {
          "id": "GPIO12",
          "input": "Yes",
          "output": "Yes",
          "status": "safe",
          "value": "12",
          "selectable": true,
          "note": "General-purpose GPIO (ADC2_CH2, Touch12)."
        },
        {
          "id": "GPIO13",
          "input": "Yes",
          "output": "Yes",
          "status": "safe",
          "value": "13",
          "selectable": true,
          "note": "General-purpose GPIO (ADC2_CH3, Touch13)."
        },
        {
          "id": "GPIO14",
          "input": "Yes",
          "output": "Yes",
          "status": "safe",
          "value": "14",
          "selectable": true,
          "note": "General-purpose GPIO (ADC2_CH4, Touch14)."
        },
        {
          "id": "GPIO15",
          "input": "Yes",
          "output": "Yes",
          "status": "safe",
          "value": "15",
          "selectable": true,
          "note": "General-purpose GPIO (ADC2_CH5)."
        },
        {
          "id": "GPIO16",
          "input": "Yes",
          "output": "Yes",
          "status": "safe",
          "value": "16",
          "selectable": true,
          "note": "General-purpose GPIO (ADC2_CH6)."
        },
        {
          "id": "GPIO17",
          "input": "Yes",
          "output": "Yes",
          "status": "safe",
          "value": "17",
          "selectable": true,
          "note": "General-purpose GPIO (ADC2_CH7)."
        },
        {
          "id": "GPIO18",
          "input": "Yes",
          "output": "Yes",
          "status": "safe",
          "value": "18",
          "selectable": true,
          "note": "General-purpose GPIO (ADC2_CH8)."
        },
        {
          "id": "GPIO19",
          "input": "Yes",
          "output": "Yes",
          "status": "caution",
          "value": "19",
          "selectable": true,
          "warning": "USB-Serial/JTAG D- pin by default. Use as GPIO only when USB-Serial/JTAG is not required."
        },
        {
          "id": "GPIO20",
          "input": "Yes",
          "output": "Yes",
          "status": "caution",
          "value": "20",
          "selectable": true,
          "warning": "USB-Serial/JTAG D+ pin by default. Use as GPIO only when USB-Serial/JTAG is not required."
        },
        {
          "id": "GPIO21",
          "input": "Yes",
          "output": "Yes",
          "status": "safe",
          "value": "21",
          "selectable": true,
          "note": "General-purpose GPIO. Available on ESP32-S3-WROOM modules."
        },
        {
          "id": "GPIO22",
          "input": "Yes",
          "output": "Yes",
          "status": "avoid",
          "value": "22",
          "selectable": true,
          "error": "Not a valid GPIO on ESP32-S3 (GPIO range skips GPIO22-GPIO25)."
        },
        {
          "id": "GPIO23",
          "input": "Yes",
          "output": "Yes",
          "status": "avoid",
          "value": "23",
          "selectable": true,
          "error": "Not a valid GPIO on ESP32-S3 (GPIO range skips GPIO22-GPIO25)."
        },
        {
          "id": "GPIO24",
          "input": "-",
          "output": "-",
          "status": "avoid",
          "value": "24",
          "selectable": true,
          "error": "Not a valid GPIO on ESP32-S3 (GPIO range skips GPIO22-GPIO25)."
        },
        {
          "id": "GPIO25",
          "input": "-",
          "output": "-",
          "status": "avoid",
          "value": "25",
          "selectable": true,
          "error": "Not a valid GPIO on ESP32-S3 (GPIO range skips GPIO22-GPIO25)."
        },
        {
          "id": "GPIO26",
          "input": "-",
          "output": "-",
          "status": "avoid",
          "value": "26",
          "selectable": true,
          "error": "Reserved (Flash) - GPIO26-32 connected to flash/PSRAM and not available."
        },
        {
          "id": "GPIO27",
          "input": "-",
          "output": "-",
          "status": "avoid",
          "value": "27",
          "selectable": true,
          "error": "Reserved (Flash/PSRAM)."
        },
        {
          "id": "GPIO28",
          "input": "-",
          "output": "-",
          "status": "avoid",
          "value": "28",
          "selectable": true,
          "error": "Reserved (Flash/PSRAM)."
        },
        {
          "id": "GPIO29",
          "input": "-",
          "output": "-",
          "status": "avoid",
          "value": "29",
          "selectable": true,
          "error": "Reserved (Flash/PSRAM)."
        },
        {
          "id": "GPIO30",
          "input": "-",
          "output": "-",
          "status": "avoid",
          "value": "30",
          "selectable": true,
          "error": "Reserved (Flash/PSRAM)."
        },
        {
          "id": "GPIO31",
          "input": "-",
          "output": "-",
          "status": "avoid",
          "value": "31",
          "selectable": true,
          "error": "Reserved (Flash/PSRAM)."
        },
        {
          "id": "GPIO32",
          "input": "-",
          "output": "-",
          "status": "avoid",
          "value": "32",
          "selectable": true,
          "error": "Reserved (Flash/PSRAM)."
        },
        {
          "id": "GPIO33",
          "input": "Yes",
          "output": "Yes",
          "status": "caution",
          "value": "33",
          "selectable": true,
          "warning": "General-purpose GPIO on some ESP32-S3 variants; may be reserved for Octal flash/PSRAM on S3R8/R8V-class modules. Verify module variant."
        },
        {
          "id": "GPIO34",
          "input": "Yes",
          "output": "Yes",
          "status": "caution",
          "value": "34",
          "selectable": true,
          "warning": "General-purpose GPIO on some ESP32-S3 variants; may be reserved for Octal flash/PSRAM on S3R8/R8V-class modules. Verify module variant."
        },
        {
          "id": "GPIO35",
          "input": "Yes",
          "output": "Yes*",
          "status": "caution",
          "value": "35",
          "selectable": true,
          "warning": "General-purpose GPIO on some ESP32-S3 variants; may be reserved for Octal flash/PSRAM on S3R8/R8V-class modules. Verify module variant."
        },
        {
          "id": "GPIO36",
          "input": "Yes",
          "output": "Yes*",
          "status": "caution",
          "value": "36",
          "selectable": true,
          "warning": "General-purpose GPIO on some ESP32-S3 variants; may be reserved for Octal flash/PSRAM on S3R8/R8V-class modules. Verify module variant."
        },
        {
          "id": "GPIO37",
          "input": "Yes",
          "output": "Yes*",
          "status": "caution",
          "value": "37",
          "selectable": true,
          "warning": "General-purpose GPIO on some ESP32-S3 variants; may be reserved for Octal flash/PSRAM on S3R8/R8V-class modules. Verify module variant."
        },
        {
          "id": "GPIO38",
          "input": "Yes",
          "output": "Yes",
          "status": "safe",
          "value": "38",
          "selectable": true,
          "note": "General-purpose GPIO."
        },
        {
          "id": "GPIO39",
          "input": "Yes",
          "output": "Yes",
          "status": "safe",
          "value": "39",
          "selectable": true,
          "note": "General-purpose GPIO."
        },
        {
          "id": "GPIO40",
          "input": "Yes",
          "output": "Yes",
          "status": "safe",
          "value": "40",
          "selectable": true,
          "note": "General-purpose GPIO."
        },
        {
          "id": "GPIO41",
          "input": "Yes",
          "output": "Yes",
          "status": "safe",
          "value": "41",
          "selectable": true,
          "note": "General-purpose GPIO."
        },
        {
          "id": "GPIO42",
          "input": "Yes",
          "output": "Yes",
          "status": "safe",
          "value": "42",
          "selectable": true,
          "note": "General-purpose GPIO."
        },
        {
          "id": "GPIO43",
          "input": "Yes (UART0 RX)",
          "output": "Yes*",
          "status": "caution",
          "value": "43",
          "selectable": true,
          "warning": "UART0 RX connected to USB-UART. Keep for programming."
        },
        {
          "id": "GPIO44",
          "input": "Yes*",
          "output": "Yes (UART0 TX)",
          "status": "caution",
          "value": "44",
          "selectable": true,
          "warning": "UART0 TX connected to USB-UART. Emits boot logs."
        },
        {
          "id": "GPIO45",
          "input": "Yes",
          "output": "Yes",
          "status": "caution",
          "value": "45",
          "selectable": true,
          "warning": "Strapping pin for VDD_SPI/flash-voltage selection. Keep the required default level at reset; avoid external pulls that change boot configuration."
        },
        {
          "id": "GPIO46",
          "input": "Yes",
          "output": "Yes",
          "status": "caution",
          "value": "46",
          "selectable": true,
          "warning": "Strapping - participates in boot mode selection and ROM log control. Avoid pull-ups to VCC."
        },
        {
          "id": "GPIO47",
          "input": "Yes",
          "output": "Yes",
          "status": "safe",
          "value": "47",
          "selectable": true,
          "note": "General-purpose GPIO."
        },
        {
          "id": "GPIO48",
          "input": "Yes",
          "output": "Yes",
          "status": "safe",
          "value": "48",
          "selectable": true,
          "note": "General-purpose GPIO. On DevKitC controls RGB LED blue channel."
        }
      ]
    },
    "esp32-c2": {
      "key": "esp32-c2",
      "title": "ESP32-C2 (ESP8684)",
      "notes": [
        "ESP32-C2/ESP8684: GPIO8 and GPIO9 are strapping pins and must not be forced to an invalid level during reset.",
        "For SiP-flash variants, GPIO11-17 are dedicated to flash; GPIO0-7, GPIO10, and GPIO18-20 are normal GPIO unless board wiring says otherwise.",
        "GPIO19 and GPIO20 are commonly used for UART0 programming/logs; reuse only if flashing/logging is not affected.",
        "ADC/RTC alternate functions do not by themselves make a pin caution."
      ],
      "rows": [
        {
          "id": "GPIO0",
          "input": "Yes (ADC1_CH0)",
          "output": "Yes",
          "status": "safe",
          "value": "0",
          "selectable": true,
          "note": "General-purpose GPIO. On DevKitC-02 drives red LED."
        },
        {
          "id": "GPIO1",
          "input": "Yes (ADC1_CH1)",
          "output": "Yes",
          "status": "safe",
          "value": "1",
          "selectable": true,
          "note": "General-purpose GPIO. On DevKit drives green LED."
        },
        {
          "id": "GPIO2",
          "input": "Yes (ADC1_CH2)",
          "output": "Yes",
          "status": "safe",
          "value": "2",
          "selectable": true,
          "note": "General-purpose GPIO. Recommended as I2C SDA."
        },
        {
          "id": "GPIO3",
          "input": "Yes (ADC1_CH3)",
          "output": "Yes",
          "status": "safe",
          "value": "3",
          "selectable": true,
          "note": "General-purpose GPIO. Recommended as I2C SCL."
        },
        {
          "id": "GPIO4",
          "input": "Yes (ADC1_CH4)",
          "output": "Yes*",
          "status": "safe",
          "value": "4",
          "selectable": true,
          "note": "General-purpose GPIO (ADC1_CH4, RTC)."
        },
        {
          "id": "GPIO5",
          "input": "Yes (ADC2_CH0)",
          "output": "Yes*",
          "status": "safe",
          "value": "5",
          "selectable": true,
          "note": "General-purpose GPIO. ADC2 analog reads may conflict with Wi-Fi; digital IO is fine."
        },
        {
          "id": "GPIO6",
          "input": "Yes",
          "output": "Yes*",
          "status": "safe",
          "value": "6",
          "selectable": true,
          "note": "General-purpose GPIO."
        },
        {
          "id": "GPIO7",
          "input": "Yes",
          "output": "Yes*",
          "status": "safe",
          "value": "7",
          "selectable": true,
          "note": "General-purpose GPIO."
        },
        {
          "id": "GPIO8",
          "input": "Yes",
          "output": "Yes",
          "status": "caution",
          "value": "8",
          "selectable": true,
          "warning": "Strapping - affects boot mode. Do not pull LOW during reset. On DevKit drives blue LED."
        },
        {
          "id": "GPIO9",
          "input": "Yes",
          "output": "Yes",
          "status": "caution",
          "value": "9",
          "selectable": true,
          "warning": "Strapping - boot/log strap. Internal pull-up. Avoid forcing LOW at boot."
        },
        {
          "id": "GPIO10",
          "input": "Yes",
          "output": "Yes*",
          "status": "safe",
          "value": "10",
          "selectable": true,
          "note": "General-purpose GPIO."
        },
        {
          "id": "GPIO18",
          "input": "Yes",
          "output": "Yes",
          "status": "safe",
          "value": "18",
          "selectable": true,
          "note": "General-purpose GPIO. Safe digital IO."
        },
        {
          "id": "GPIO19",
          "input": "Yes (UART0 RX)",
          "output": "Yes*",
          "status": "caution",
          "value": "19",
          "selectable": true,
          "warning": "UART0 RX for programming. Keep free when flashing."
        },
        {
          "id": "GPIO20",
          "input": "Yes*",
          "output": "Yes (UART0 TX)",
          "status": "caution",
          "value": "20",
          "selectable": true,
          "warning": "UART0 TX for boot logs and programming. Avoid using for peripherals."
        }
      ]
    },
    "esp32-c3": {
      "key": "esp32-c3",
      "title": "ESP32-C3 (ESP32-C3-WROOM-02)",
      "notes": [
        "ESP32-C3: GPIO2, GPIO8, and GPIO9 are strapping pins sampled during reset.",
        "GPIO12-17 are normally used for SPI flash/PSRAM and are not recommended for GPIO.",
        "GPIO18 and GPIO19 are used by USB-Serial/JTAG by default; using them as GPIO disables that function.",
        "GPIO20 and GPIO21 are commonly UART0 RX/TX pins for programming/logs.",
        "GPIO5 is ADC2; analog reads can conflict with Wi-Fi, but digital GPIO use is normal."
      ],
      "rows": [
        {
          "id": "GPIO0",
          "input": "Yes (ADC1_CH0)",
          "output": "Yes",
          "status": "safe",
          "value": "0",
          "selectable": true,
          "note": "General-purpose GPIO. Also RTC 32k_XP when using external 32kHz oscillator."
        },
        {
          "id": "GPIO1",
          "input": "Yes (ADC1_CH1)",
          "output": "Yes",
          "status": "safe",
          "value": "1",
          "selectable": true,
          "note": "General-purpose GPIO. Also RTC 32k_XN when using external 32kHz oscillator."
        },
        {
          "id": "GPIO2",
          "input": "Yes (ADC1_CH2)",
          "output": "Yes",
          "status": "caution",
          "value": "2",
          "selectable": true,
          "warning": "Strapping - participates in boot mode selection. Avoid pull-up at reset."
        },
        {
          "id": "GPIO3",
          "input": "Yes (ADC1_CH3)",
          "output": "Yes",
          "status": "safe",
          "value": "3",
          "selectable": true,
          "note": "General-purpose GPIO."
        },
        {
          "id": "GPIO4",
          "input": "Yes (ADC1_CH4)",
          "output": "Yes",
          "status": "safe",
          "value": "4",
          "selectable": true,
          "note": "General-purpose GPIO."
        },
        {
          "id": "GPIO5",
          "input": "Yes (ADC2_CH0)",
          "output": "Yes",
          "status": "safe",
          "value": "5",
          "selectable": true,
          "note": "General-purpose GPIO. ADC2 analog reads may conflict with Wi-Fi; digital IO is fine."
        },
        {
          "id": "GPIO6",
          "input": "Yes",
          "output": "Yes",
          "status": "safe",
          "value": "6",
          "selectable": true,
          "note": "General-purpose GPIO. Commonly used as SPI SCLK on some boards."
        },
        {
          "id": "GPIO7",
          "input": "Yes",
          "output": "Yes",
          "status": "safe",
          "value": "7",
          "selectable": true,
          "note": "General-purpose GPIO. Commonly used as SPI MOSI on some boards."
        },
        {
          "id": "GPIO8",
          "input": "Yes",
          "output": "Yes",
          "status": "caution",
          "value": "8",
          "selectable": true,
          "warning": "Strapping - controls ROM log output and boot mode. Often drives blue LED."
        },
        {
          "id": "GPIO9",
          "input": "Yes",
          "output": "Yes",
          "status": "caution",
          "value": "9",
          "selectable": true,
          "warning": "Strapping - bootloader strap. Tied to BOOT button on dev kits."
        },
        {
          "id": "GPIO10",
          "input": "Yes",
          "output": "Yes",
          "status": "safe",
          "value": "10",
          "selectable": true,
          "note": "General-purpose GPIO. Default SPI CS1 on some boards."
        },
        {
          "id": "GPIO11",
          "input": "-",
          "output": "-",
          "status": "avoid",
          "value": "11",
          "selectable": true,
          "error": "Not available as GPIO."
        },
        {
          "id": "GPIO12",
          "input": "-",
          "output": "-",
          "status": "avoid",
          "value": "12",
          "selectable": true,
          "error": "Not available as GPIO."
        },
        {
          "id": "GPIO13",
          "input": "-",
          "output": "-",
          "status": "avoid",
          "value": "13",
          "selectable": true,
          "error": "Not available as GPIO."
        },
        {
          "id": "GPIO14",
          "input": "-",
          "output": "-",
          "status": "avoid",
          "value": "14",
          "selectable": true,
          "error": "Not available as GPIO."
        },
        {
          "id": "GPIO15",
          "input": "-",
          "output": "-",
          "status": "avoid",
          "value": "15",
          "selectable": true,
          "error": "Not available as GPIO."
        },
        {
          "id": "GPIO16",
          "input": "-",
          "output": "-",
          "status": "avoid",
          "value": "16",
          "selectable": true,
          "error": "Not available as GPIO."
        },
        {
          "id": "GPIO17",
          "input": "-",
          "output": "-",
          "status": "avoid",
          "value": "17",
          "selectable": true,
          "error": "Not available as GPIO."
        },
        {
          "id": "GPIO18",
          "input": "Yes",
          "output": "Yes",
          "status": "caution",
          "value": "18",
          "selectable": true,
          "warning": "USB-Serial/JTAG default D- (USB_JTAG_TMS). Keep free if using USB-JTAG."
        },
        {
          "id": "GPIO19",
          "input": "Yes",
          "output": "Yes",
          "status": "caution",
          "value": "19",
          "selectable": true,
          "warning": "USB-Serial/JTAG default D+ (USB_JTAG_TCK). Keep free if using USB-JTAG."
        },
        {
          "id": "GPIO20",
          "input": "Yes (UART0 RX)",
          "output": "Yes*",
          "status": "caution",
          "value": "20",
          "selectable": true,
          "warning": "UART0 RX for programming/logs. Avoid strong external drive during flashing."
        },
        {
          "id": "GPIO21",
          "input": "Yes*",
          "output": "Yes (UART0 TX)",
          "status": "caution",
          "value": "21",
          "selectable": true,
          "warning": "UART0 TX outputs boot logs and is used during flashing. Avoid connecting sensitive peripherals."
        }
      ]
    },
    "esp32-c5": {
      "key": "esp32-c5",
      "title": "ESP32-C5 (ESP32-C5-WROOM-1)",
      "notes": [
        "ESP32-C5: GPIO2, GPIO7, GPIO25, GPIO27, and GPIO28 are strapping pins in current ESP-IDF documentation.",
        "GPIO16-22 are normally used for SPI flash/PSRAM and are not recommended for GPIO.",
        "GPIO13 and GPIO14 are used by USB-JTAG by default; using them as GPIO disables USB-JTAG.",
        "GPIO11 and GPIO12 may be used as UART0 on boards that expose UART flashing/logs.",
        "ESP32-C5 has GPIO0-GPIO28 only; GPIO29 and higher are not valid GPIOs for this chip."
      ],
      "rows": [
        {
          "id": "GPIO0",
          "input": "Yes",
          "output": "Yes",
          "status": "safe",
          "value": "0",
          "selectable": true,
          "note": "General-purpose GPIO."
        },
        {
          "id": "GPIO1",
          "input": "Yes",
          "output": "Yes",
          "status": "safe",
          "value": "1",
          "selectable": true,
          "note": "General-purpose GPIO."
        },
        {
          "id": "GPIO2",
          "input": "Yes",
          "output": "Yes",
          "status": "caution",
          "value": "2",
          "selectable": true,
          "warning": "Strapping pin sampled during reset. Keep the required default boot level."
        },
        {
          "id": "GPIO3",
          "input": "Yes",
          "output": "Yes",
          "status": "safe",
          "value": "3",
          "selectable": true,
          "note": "General-purpose GPIO (ADC1_CH2)."
        },
        {
          "id": "GPIO4",
          "input": "Yes",
          "output": "Yes",
          "status": "safe",
          "value": "4",
          "selectable": true,
          "note": "General-purpose GPIO (ADC1_CH3)."
        },
        {
          "id": "GPIO5",
          "input": "Yes",
          "output": "Yes",
          "status": "safe",
          "value": "5",
          "selectable": true,
          "note": "General-purpose GPIO (ADC1_CH4)."
        },
        {
          "id": "GPIO6",
          "input": "Yes",
          "output": "Yes",
          "status": "safe",
          "value": "6",
          "selectable": true,
          "note": "General-purpose GPIO."
        },
        {
          "id": "GPIO7",
          "input": "Yes",
          "output": "Yes",
          "status": "caution",
          "value": "7",
          "selectable": true,
          "warning": "Strapping pin sampled during reset. Keep the required default boot level."
        },
        {
          "id": "GPIO8",
          "input": "Yes",
          "output": "Yes",
          "status": "safe",
          "value": "8",
          "selectable": true,
          "note": "General-purpose GPIO."
        },
        {
          "id": "GPIO9",
          "input": "Yes",
          "output": "Yes",
          "status": "safe",
          "value": "9",
          "selectable": true,
          "note": "General-purpose GPIO."
        },
        {
          "id": "GPIO10",
          "input": "Yes",
          "output": "Yes",
          "status": "safe",
          "value": "10",
          "selectable": true,
          "note": "General-purpose GPIO."
        },
        {
          "id": "GPIO11",
          "input": "Yes*",
          "output": "Yes",
          "status": "caution",
          "value": "11",
          "selectable": true,
          "warning": "UART0 TX on some boards. Use as GPIO only if UART flashing/logging is not required."
        },
        {
          "id": "GPIO12",
          "input": "Yes",
          "output": "Yes*",
          "status": "caution",
          "value": "12",
          "selectable": true,
          "warning": "UART0 RX on some boards. Use as GPIO only if UART flashing/logging is not required."
        },
        {
          "id": "GPIO13",
          "input": "Yes",
          "output": "Yes",
          "status": "caution",
          "value": "13",
          "selectable": true,
          "warning": "USB-JTAG D- pin by default. Use as GPIO only when USB-JTAG is not required."
        },
        {
          "id": "GPIO14",
          "input": "Yes",
          "output": "Yes",
          "status": "caution",
          "value": "14",
          "selectable": true,
          "warning": "USB-JTAG D+ pin by default. Use as GPIO only when USB-JTAG is not required."
        },
        {
          "id": "GPIO15",
          "input": "Yes",
          "output": "Yes",
          "status": "safe",
          "value": "15",
          "selectable": true,
          "note": "General-purpose GPIO."
        },
        {
          "id": "GPIO16",
          "input": "Yes",
          "output": "Yes*",
          "status": "avoid",
          "value": "16",
          "selectable": true,
          "error": "SPI0/1 Flash - used by external flash. Do not use unless you know your module wiring."
        },
        {
          "id": "GPIO17",
          "input": "Yes",
          "output": "Yes*",
          "status": "avoid",
          "value": "17",
          "selectable": true,
          "error": "SPI0/1 Flash - used by external flash. Do not use unless you know your module wiring."
        },
        {
          "id": "GPIO18",
          "input": "Yes",
          "output": "Yes*",
          "status": "avoid",
          "value": "18",
          "selectable": true,
          "error": "SPI0/1 Flash - used by external flash. Do not use unless you know your module wiring."
        },
        {
          "id": "GPIO19",
          "input": "Yes",
          "output": "Yes*",
          "status": "avoid",
          "value": "19",
          "selectable": true,
          "error": "SPI0/1 Flash - used by external flash. Do not use unless you know your module wiring."
        },
        {
          "id": "GPIO20",
          "input": "Yes",
          "output": "Yes*",
          "status": "avoid",
          "value": "20",
          "selectable": true,
          "error": "SPI0/1 Flash - used by external flash. Do not use unless you know your module wiring."
        },
        {
          "id": "GPIO21",
          "input": "Yes",
          "output": "Yes*",
          "status": "avoid",
          "value": "21",
          "selectable": true,
          "error": "SPI0/1 Flash - used by external flash. Do not use unless you know your module wiring."
        },
        {
          "id": "GPIO22",
          "input": "Yes",
          "output": "Yes*",
          "status": "avoid",
          "value": "22",
          "selectable": true,
          "error": "SPI0/1 Flash - used by external flash. Do not use unless you know your module wiring."
        },
        {
          "id": "GPIO23",
          "input": "Yes",
          "output": "Yes",
          "status": "safe",
          "value": "23",
          "selectable": true,
          "note": "General-purpose GPIO."
        },
        {
          "id": "GPIO24",
          "input": "Yes",
          "output": "Yes",
          "status": "safe",
          "value": "24",
          "selectable": true,
          "note": "General-purpose GPIO."
        },
        {
          "id": "GPIO25",
          "input": "Yes",
          "output": "Yes",
          "status": "caution",
          "value": "25",
          "selectable": true,
          "warning": "Strapping pin sampled during reset. Keep the required default boot level."
        },
        {
          "id": "GPIO26",
          "input": "Yes",
          "output": "Yes",
          "status": "safe",
          "value": "26",
          "selectable": true,
          "note": "General-purpose GPIO."
        },
        {
          "id": "GPIO27",
          "input": "Yes",
          "output": "Yes",
          "status": "caution",
          "value": "27",
          "selectable": true,
          "warning": "Strapping pin sampled during reset. Keep the required default boot level."
        },
        {
          "id": "GPIO28",
          "input": "Yes",
          "output": "Yes",
          "status": "caution",
          "value": "28",
          "selectable": true,
          "warning": "Strapping pin sampled during reset. Keep the required default boot level."
        },
        {
          "id": "GPIO29",
          "input": "Yes",
          "output": "Yes",
          "status": "avoid",
          "value": "29",
          "selectable": true,
          "error": "Not a valid GPIO on ESP32-C5 (official GPIO range is GPIO0-GPIO28)."
        },
        {
          "id": "GPIO30",
          "input": "Yes",
          "output": "Yes",
          "status": "avoid",
          "value": "30",
          "selectable": true,
          "error": "Not a valid GPIO on ESP32-C5 (official GPIO range is GPIO0-GPIO28)."
        },
        {
          "id": "GPIO31",
          "input": "Yes",
          "output": "Yes",
          "status": "avoid",
          "value": "31",
          "selectable": true,
          "error": "Not a valid GPIO on ESP32-C5 (official GPIO range is GPIO0-GPIO28)."
        },
        {
          "id": "GPIO32",
          "input": "Yes",
          "output": "Yes",
          "status": "avoid",
          "value": "32",
          "selectable": true,
          "error": "Not a valid GPIO on ESP32-C5 (official GPIO range is GPIO0-GPIO28)."
        },
        {
          "id": "GPIO33",
          "input": "Yes",
          "output": "Yes",
          "status": "avoid",
          "value": "33",
          "selectable": true,
          "error": "Not a valid GPIO on ESP32-C5 (official GPIO range is GPIO0-GPIO28)."
        },
        {
          "id": "GPIO34",
          "input": "Yes",
          "output": "Yes",
          "status": "avoid",
          "value": "34",
          "selectable": true,
          "error": "Not a valid GPIO on ESP32-C5 (official GPIO range is GPIO0-GPIO28)."
        },
        {
          "id": "GPIO35",
          "input": "Yes",
          "output": "Yes",
          "status": "avoid",
          "value": "35",
          "selectable": true,
          "error": "Not a valid GPIO on ESP32-C5 (official GPIO range is GPIO0-GPIO28)."
        },
        {
          "id": "GPIO36",
          "input": "Yes",
          "output": "Yes",
          "status": "avoid",
          "value": "36",
          "selectable": true,
          "error": "Not a valid GPIO on ESP32-C5 (official GPIO range is GPIO0-GPIO28)."
        },
        {
          "id": "GPIO37",
          "input": "Yes",
          "output": "Yes",
          "status": "avoid",
          "value": "37",
          "selectable": true,
          "error": "Not a valid GPIO on ESP32-C5 (official GPIO range is GPIO0-GPIO28)."
        },
        {
          "id": "GPIO38",
          "input": "Yes",
          "output": "Yes",
          "status": "avoid",
          "value": "38",
          "selectable": true,
          "error": "Not a valid GPIO on ESP32-C5 (official GPIO range is GPIO0-GPIO28)."
        },
        {
          "id": "GPIO39",
          "input": "Yes",
          "output": "Yes",
          "status": "avoid",
          "value": "39",
          "selectable": true,
          "error": "Not a valid GPIO on ESP32-C5 (official GPIO range is GPIO0-GPIO28)."
        }
      ]
    },
    "esp32-c6": {
      "key": "esp32-c6",
      "title": "ESP32-C6 (ESP32-C6-WROOM-1)",
      "notes": [
        "ESP32-C6: GPIO4, GPIO5, GPIO8, GPIO9, and GPIO15 are strapping pins sampled during reset.",
        "GPIO12 and GPIO13 are used by USB-JTAG by default; using them as GPIO disables USB-JTAG.",
        "GPIO24-30 are normally used for SPI flash/PSRAM and are not recommended for GPIO.",
        "ESP32-C6 has GPIO0-GPIO30 only; GPIO34-GPIO38 are not valid GPIOs for this chip.",
        "GPIO2, GPIO3, GPIO7, GPIO16-GPIO23 are normal GPIOs unless board wiring reserves them."
      ],
      "rows": [
        {
          "id": "GPIO0",
          "input": "Yes",
          "output": "Yes",
          "status": "safe",
          "value": "0",
          "selectable": true,
          "note": "General-purpose GPIO."
        },
        {
          "id": "GPIO1",
          "input": "Yes",
          "output": "Yes",
          "status": "safe",
          "value": "1",
          "selectable": true,
          "note": "General-purpose GPIO."
        },
        {
          "id": "GPIO2",
          "input": "Yes",
          "output": "Yes",
          "status": "safe",
          "value": "2",
          "selectable": true,
          "note": "General-purpose GPIO."
        },
        {
          "id": "GPIO3",
          "input": "Yes",
          "output": "Yes",
          "status": "safe",
          "value": "3",
          "selectable": true,
          "note": "General-purpose GPIO."
        },
        {
          "id": "GPIO4",
          "input": "Yes",
          "output": "Yes",
          "status": "caution",
          "value": "4",
          "selectable": true,
          "warning": "Strapping pin sampled during reset. Keep the required default boot level."
        },
        {
          "id": "GPIO5",
          "input": "Yes",
          "output": "Yes",
          "status": "caution",
          "value": "5",
          "selectable": true,
          "warning": "Strapping pin sampled during reset. Keep the required default boot level."
        },
        {
          "id": "GPIO6",
          "input": "Yes",
          "output": "Yes",
          "status": "safe",
          "value": "6",
          "selectable": true,
          "note": "General-purpose GPIO."
        },
        {
          "id": "GPIO7",
          "input": "Yes",
          "output": "Yes",
          "status": "safe",
          "value": "7",
          "selectable": true,
          "note": "General-purpose GPIO."
        },
        {
          "id": "GPIO8",
          "input": "Yes",
          "output": "Yes",
          "status": "caution",
          "value": "8",
          "selectable": true,
          "warning": "Strapping pin sampled during reset. Keep the required default boot level."
        },
        {
          "id": "GPIO9",
          "input": "Yes",
          "output": "Yes",
          "status": "caution",
          "value": "9",
          "selectable": true,
          "warning": "Strapping pin sampled during reset. Keep the required default boot level."
        },
        {
          "id": "GPIO10",
          "input": "Yes",
          "output": "Yes",
          "status": "safe",
          "value": "10",
          "selectable": true,
          "note": "General-purpose GPIO."
        },
        {
          "id": "GPIO11",
          "input": "Yes",
          "output": "Yes",
          "status": "safe",
          "value": "11",
          "selectable": true,
          "note": "General-purpose GPIO."
        },
        {
          "id": "GPIO12",
          "input": "Yes",
          "output": "Yes",
          "status": "caution",
          "value": "12",
          "selectable": true,
          "warning": "USB-JTAG D- pin by default. Use as GPIO only when USB-JTAG is not required."
        },
        {
          "id": "GPIO13",
          "input": "Yes",
          "output": "Yes",
          "status": "caution",
          "value": "13",
          "selectable": true,
          "warning": "USB-JTAG D+ pin by default. Use as GPIO only when USB-JTAG is not required."
        },
        {
          "id": "GPIO14",
          "input": "Yes",
          "output": "Yes",
          "status": "safe",
          "value": "14",
          "selectable": true,
          "note": "General-purpose GPIO."
        },
        {
          "id": "GPIO15",
          "input": "Yes",
          "output": "Yes",
          "status": "caution",
          "value": "15",
          "selectable": true,
          "warning": "Strapping pin sampled during reset. Keep the required default boot level."
        },
        {
          "id": "GPIO16",
          "input": "Yes",
          "output": "Yes*",
          "status": "safe",
          "value": "16",
          "selectable": true,
          "note": "General-purpose GPIO."
        },
        {
          "id": "GPIO17",
          "input": "Yes",
          "output": "Yes*",
          "status": "safe",
          "value": "17",
          "selectable": true,
          "note": "General-purpose GPIO."
        },
        {
          "id": "GPIO18",
          "input": "Yes",
          "output": "Yes*",
          "status": "safe",
          "value": "18",
          "selectable": true,
          "note": "General-purpose GPIO."
        },
        {
          "id": "GPIO19",
          "input": "Yes",
          "output": "Yes*",
          "status": "safe",
          "value": "19",
          "selectable": true,
          "note": "General-purpose GPIO."
        },
        {
          "id": "GPIO20",
          "input": "Yes",
          "output": "Yes*",
          "status": "safe",
          "value": "20",
          "selectable": true,
          "note": "General-purpose GPIO."
        },
        {
          "id": "GPIO21",
          "input": "Yes",
          "output": "Yes*",
          "status": "safe",
          "value": "21",
          "selectable": true,
          "note": "General-purpose GPIO."
        },
        {
          "id": "GPIO22",
          "input": "Yes",
          "output": "Yes*",
          "status": "safe",
          "value": "22",
          "selectable": true,
          "note": "General-purpose GPIO."
        },
        {
          "id": "GPIO23",
          "input": "Yes",
          "output": "Yes",
          "status": "safe",
          "value": "23",
          "selectable": true,
          "note": "General-purpose GPIO."
        },
        {
          "id": "GPIO24",
          "input": "Yes",
          "output": "Yes",
          "status": "avoid",
          "value": "24",
          "selectable": true,
          "error": "SPI0/1 flash/PSRAM interface on ESP32-C6 modules. Do not use unless board documentation explicitly confirms it is free."
        },
        {
          "id": "GPIO25",
          "input": "Yes",
          "output": "Yes",
          "status": "avoid",
          "value": "25",
          "selectable": true,
          "error": "SPI0/1 flash/PSRAM interface on ESP32-C6 modules. Do not use unless board documentation explicitly confirms it is free."
        },
        {
          "id": "GPIO34",
          "input": "Yes",
          "output": "Yes",
          "status": "avoid",
          "value": "34",
          "selectable": true,
          "error": "Not a valid GPIO on ESP32-C6 (official GPIO range is GPIO0-GPIO30)."
        },
        {
          "id": "GPIO35",
          "input": "Yes",
          "output": "Yes",
          "status": "avoid",
          "value": "35",
          "selectable": true,
          "error": "Not a valid GPIO on ESP32-C6 (official GPIO range is GPIO0-GPIO30)."
        },
        {
          "id": "GPIO36",
          "input": "Yes",
          "output": "Yes",
          "status": "avoid",
          "value": "36",
          "selectable": true,
          "error": "Not a valid GPIO on ESP32-C6 (official GPIO range is GPIO0-GPIO30)."
        },
        {
          "id": "GPIO37",
          "input": "Yes",
          "output": "Yes",
          "status": "avoid",
          "value": "37",
          "selectable": true,
          "error": "Not a valid GPIO on ESP32-C6 (official GPIO range is GPIO0-GPIO30)."
        },
        {
          "id": "GPIO38",
          "input": "Yes",
          "output": "Yes",
          "status": "avoid",
          "value": "38",
          "selectable": true,
          "error": "Not a valid GPIO on ESP32-C6 (official GPIO range is GPIO0-GPIO30)."
        }
      ]
    },
    "esp32-h2": {
      "key": "esp32-h2",
      "title": "ESP32-H2 (ESP32-H2-MINI-1)",
      "notes": [
        "ESP32-H2: GPIO2, GPIO3, GPIO8, GPIO9, and GPIO25 are strapping pins sampled during reset.",
        "For SiP-flash variants, GPIO15-21 are dedicated to SPI flash, and GPIO6-7 are not led out.",
        "GPIO26 and GPIO27 are used by USB-Serial-JTAG by default; using them as GPIO disables that function.",
        "GPIO0-5, GPIO8-14, and GPIO22-27 are the user-available ranges on SiP-flash variants, subject to strapping and USB/JTAG caveats.",
        "Analog comparator or RTC alternate functions do not by themselves make a pin caution."
      ],
      "rows": [
        {
          "id": "GPIO0",
          "input": "Yes (ADC1_CH0)",
          "output": "Yes",
          "status": "safe",
          "value": "0",
          "selectable": true,
          "note": "General-purpose GPIO."
        },
        {
          "id": "GPIO1",
          "input": "Yes (ADC1_CH1)",
          "output": "Yes",
          "status": "safe",
          "value": "1",
          "selectable": true,
          "note": "General-purpose GPIO (ADC1_CH0)."
        },
        {
          "id": "GPIO2",
          "input": "Yes (ADC1_CH2)",
          "output": "Yes",
          "status": "caution",
          "value": "2",
          "selectable": true,
          "warning": "Strapping pin sampled during reset. Keep the required default boot level."
        },
        {
          "id": "GPIO3",
          "input": "Yes (ADC1_CH3)",
          "output": "Yes",
          "status": "caution",
          "value": "3",
          "selectable": true,
          "warning": "Strapping pin sampled during reset. Keep the required default boot level."
        },
        {
          "id": "GPIO4",
          "input": "Yes (ADC1_CH4)",
          "output": "Yes",
          "status": "safe",
          "value": "4",
          "selectable": true,
          "note": "General-purpose GPIO (ADC1_CH3)."
        },
        {
          "id": "GPIO5",
          "input": "Yes (ADC1_CH5)",
          "output": "Yes",
          "status": "safe",
          "value": "5",
          "selectable": true,
          "note": "General-purpose GPIO (ADC1_CH4)."
        },
        {
          "id": "GPIO6",
          "input": "-",
          "output": "-",
          "status": "avoid",
          "value": "6",
          "selectable": true,
          "error": "Not led out on ESP32-H2 SiP-flash variants; avoid unless your exact chip/package exposes it."
        },
        {
          "id": "GPIO7",
          "input": "-",
          "output": "-",
          "status": "avoid",
          "value": "7",
          "selectable": true,
          "error": "Not led out on ESP32-H2 SiP-flash variants; avoid unless your exact chip/package exposes it."
        },
        {
          "id": "GPIO8",
          "input": "Yes",
          "output": "Yes",
          "status": "caution",
          "value": "8",
          "selectable": true,
          "warning": "Strapping pin sampled during reset. Keep the required default boot level."
        },
        {
          "id": "GPIO9",
          "input": "Yes",
          "output": "Yes",
          "status": "caution",
          "value": "9",
          "selectable": true,
          "warning": "Strapping pin sampled during reset. Keep the required default boot level."
        },
        {
          "id": "GPIO10",
          "input": "Yes (ZCD0)",
          "output": "Yes",
          "status": "safe",
          "value": "10",
          "selectable": true,
          "note": "General-purpose GPIO with analog comparator reference function."
        },
        {
          "id": "GPIO11",
          "input": "Yes (ZCD1)",
          "output": "Yes",
          "status": "safe",
          "value": "11",
          "selectable": true,
          "note": "General-purpose GPIO with analog comparator input function."
        },
        {
          "id": "GPIO12",
          "input": "Yes",
          "output": "Yes",
          "status": "safe",
          "value": "12",
          "selectable": true,
          "note": "General-purpose GPIO."
        },
        {
          "id": "GPIO13",
          "input": "Yes (XTAL_32K_P)",
          "output": "Yes",
          "status": "safe",
          "value": "13",
          "selectable": true,
          "note": "General-purpose GPIO. Also RTC/32 kHz oscillator-capable pin; verify if using an external 32 kHz crystal."
        },
        {
          "id": "GPIO14",
          "input": "Yes (XTAL_32K_N)",
          "output": "Yes",
          "status": "safe",
          "value": "14",
          "selectable": true,
          "note": "General-purpose GPIO. Also RTC/32 kHz oscillator-capable pin; verify if using an external 32 kHz crystal."
        },
        {
          "id": "GPIO15",
          "input": "-",
          "output": "-",
          "status": "avoid",
          "value": "15",
          "selectable": true,
          "error": "SPI0/1 flash interface on ESP32-H2 SiP-flash variants. Do not use as GPIO."
        },
        {
          "id": "GPIO16",
          "input": "-",
          "output": "-",
          "status": "avoid",
          "value": "16",
          "selectable": true,
          "error": "SPI0/1 flash interface on ESP32-H2 SiP-flash variants. Do not use as GPIO."
        },
        {
          "id": "GPIO17",
          "input": "-",
          "output": "-",
          "status": "avoid",
          "value": "17",
          "selectable": true,
          "error": "SPI0/1 flash interface on ESP32-H2 SiP-flash variants. Do not use as GPIO."
        },
        {
          "id": "GPIO18",
          "input": "-",
          "output": "-",
          "status": "avoid",
          "value": "18",
          "selectable": true,
          "error": "SPI0/1 flash interface on ESP32-H2 SiP-flash variants. Do not use as GPIO."
        },
        {
          "id": "GPIO19",
          "input": "-",
          "output": "-",
          "status": "avoid",
          "value": "19",
          "selectable": true,
          "error": "SPI0/1 flash interface on ESP32-H2 SiP-flash variants. Do not use as GPIO."
        },
        {
          "id": "GPIO20",
          "input": "-",
          "output": "-",
          "status": "avoid",
          "value": "20",
          "selectable": true,
          "error": "SPI0/1 flash interface on ESP32-H2 SiP-flash variants. Do not use as GPIO."
        },
        {
          "id": "GPIO21",
          "input": "-",
          "output": "-",
          "status": "avoid",
          "value": "21",
          "selectable": true,
          "error": "SPI0/1 flash interface on ESP32-H2 SiP-flash variants. Do not use as GPIO."
        },
        {
          "id": "GPIO22",
          "input": "Yes",
          "output": "Yes",
          "status": "safe",
          "value": "22",
          "selectable": true,
          "note": "General-purpose GPIO."
        },
        {
          "id": "GPIO23",
          "input": "Yes (UART0 RX)",
          "output": "Yes*",
          "status": "caution",
          "value": "23",
          "selectable": true,
          "warning": "UART0 RX on some boards. Use as GPIO only if UART flashing/logging is not required."
        },
        {
          "id": "GPIO24",
          "input": "Yes*",
          "output": "Yes (UART0 TX)",
          "status": "caution",
          "value": "24",
          "selectable": true,
          "warning": "UART0 TX on some boards. Emits boot/log data when used for serial flashing/logging."
        },
        {
          "id": "GPIO25",
          "input": "Yes (FSPICS3)",
          "output": "Yes",
          "status": "caution",
          "value": "25",
          "selectable": true,
          "warning": "Strapping pin sampled during reset. Keep the required default boot level."
        },
        {
          "id": "GPIO26",
          "input": "-",
          "output": "-",
          "status": "caution",
          "value": "26",
          "selectable": true,
          "warning": "USB-Serial-JTAG D- pin by default. Use as GPIO only when USB-Serial-JTAG is not required."
        }
      ]
    },
    "esp32-p4": {
      "key": "esp32-p4",
      "title": "ESP32-P4 (ESP32-P4)",
      "notes": [
        "ESP32-P4: GPIO34, GPIO35, GPIO36, GPIO37, and GPIO38 are strapping pins sampled during reset.",
        "GPIO24 and GPIO25 are used by USB-JTAG by default; using them as GPIO disables USB-JTAG.",
        "GPIO0-GPIO54 are valid chip GPIOs; actual availability still depends on package and board/module routing.",
        "Touch, ADC, LP-GPIO, I2C, SPI, or other alternate functions do not by themselves make a pin caution."
      ],
      "rows": [
        {
          "id": "GPIO0",
          "input": "Yes",
          "output": "Yes",
          "status": "safe",
          "value": "0",
          "selectable": true,
          "note": "General-purpose GPIO. Verify board-level peripherals before assignment."
        },
        {
          "id": "GPIO1",
          "input": "Yes",
          "output": "Yes",
          "status": "safe",
          "value": "1",
          "selectable": true,
          "note": "General-purpose GPIO. Verify board-level peripherals before assignment."
        },
        {
          "id": "GPIO2",
          "input": "Yes",
          "output": "Yes",
          "status": "safe",
          "value": "2",
          "selectable": true,
          "note": "General-purpose GPIO. Verify board-level peripherals before assignment."
        },
        {
          "id": "GPIO3",
          "input": "Yes",
          "output": "Yes",
          "status": "safe",
          "value": "3",
          "selectable": true,
          "note": "General-purpose GPIO. Verify board-level peripherals before assignment."
        },
        {
          "id": "GPIO4",
          "input": "Yes",
          "output": "Yes",
          "status": "safe",
          "value": "4",
          "selectable": true,
          "note": "General-purpose GPIO. Verify board-level peripherals before assignment."
        },
        {
          "id": "GPIO5",
          "input": "Yes",
          "output": "Yes",
          "status": "safe",
          "value": "5",
          "selectable": true,
          "note": "General-purpose GPIO. Verify board-level peripherals before assignment."
        },
        {
          "id": "GPIO6",
          "input": "Yes",
          "output": "Yes",
          "status": "safe",
          "value": "6",
          "selectable": true,
          "note": "General-purpose GPIO. Verify board-level peripherals before assignment."
        },
        {
          "id": "GPIO7",
          "input": "Yes",
          "output": "Yes",
          "status": "safe",
          "value": "7",
          "selectable": true,
          "note": "General-purpose GPIO. Verify board-level peripherals before assignment."
        },
        {
          "id": "GPIO8",
          "input": "Yes",
          "output": "Yes",
          "status": "safe",
          "value": "8",
          "selectable": true,
          "note": "General-purpose GPIO. Verify board-level peripherals before assignment."
        },
        {
          "id": "GPIO9",
          "input": "Yes",
          "output": "Yes",
          "status": "safe",
          "value": "9",
          "selectable": true,
          "note": "General-purpose GPIO. Verify board-level peripherals before assignment."
        },
        {
          "id": "GPIO10",
          "input": "Yes",
          "output": "Yes",
          "status": "safe",
          "value": "10",
          "selectable": true,
          "note": "General-purpose GPIO. Verify board-level peripherals before assignment."
        },
        {
          "id": "GPIO11",
          "input": "Yes",
          "output": "Yes",
          "status": "safe",
          "value": "11",
          "selectable": true,
          "note": "General-purpose GPIO. Verify board-level peripherals before assignment."
        },
        {
          "id": "GPIO12",
          "input": "Yes",
          "output": "Yes",
          "status": "safe",
          "value": "12",
          "selectable": true,
          "note": "General-purpose GPIO. Verify board-level peripherals before assignment."
        },
        {
          "id": "GPIO13",
          "input": "Yes",
          "output": "Yes",
          "status": "safe",
          "value": "13",
          "selectable": true,
          "note": "General-purpose GPIO. Verify board-level peripherals before assignment."
        },
        {
          "id": "GPIO14",
          "input": "Yes",
          "output": "Yes",
          "status": "safe",
          "value": "14",
          "selectable": true,
          "note": "General-purpose GPIO. Verify board-level peripherals before assignment."
        },
        {
          "id": "GPIO15",
          "input": "Yes",
          "output": "Yes",
          "status": "safe",
          "value": "15",
          "selectable": true,
          "note": "General-purpose GPIO. Verify board-level peripherals before assignment."
        },
        {
          "id": "GPIO16",
          "input": "Yes",
          "output": "Yes",
          "status": "safe",
          "value": "16",
          "selectable": true,
          "note": "General-purpose GPIO. Verify board-level peripherals before assignment."
        },
        {
          "id": "GPIO17",
          "input": "Yes",
          "output": "Yes",
          "status": "safe",
          "value": "17",
          "selectable": true,
          "note": "General-purpose GPIO. Verify board-level peripherals before assignment."
        },
        {
          "id": "GPIO18",
          "input": "Yes",
          "output": "Yes",
          "status": "safe",
          "value": "18",
          "selectable": true,
          "note": "General-purpose GPIO. Verify board-level peripherals before assignment."
        },
        {
          "id": "GPIO19",
          "input": "Yes",
          "output": "Yes",
          "status": "safe",
          "value": "19",
          "selectable": true,
          "note": "General-purpose GPIO. Verify board-level peripherals before assignment."
        },
        {
          "id": "GPIO20",
          "input": "Yes",
          "output": "Yes",
          "status": "safe",
          "value": "20",
          "selectable": true,
          "note": "General-purpose GPIO. Verify board-level peripherals before assignment."
        },
        {
          "id": "GPIO21",
          "input": "Yes",
          "output": "Yes",
          "status": "safe",
          "value": "21",
          "selectable": true,
          "note": "General-purpose GPIO. Verify board-level peripherals before assignment."
        },
        {
          "id": "GPIO22",
          "input": "Yes",
          "output": "Yes",
          "status": "safe",
          "value": "22",
          "selectable": true,
          "note": "General-purpose GPIO. Verify board-level peripherals before assignment."
        },
        {
          "id": "GPIO23",
          "input": "Yes",
          "output": "Yes",
          "status": "safe",
          "value": "23",
          "selectable": true,
          "note": "General-purpose GPIO. Verify board-level peripherals before assignment."
        },
        {
          "id": "GPIO24",
          "input": "Yes",
          "output": "Yes",
          "status": "caution",
          "value": "24",
          "selectable": true,
          "warning": "USB-JTAG D- pin by default. Use as GPIO only when USB-JTAG is not required."
        },
        {
          "id": "GPIO25",
          "input": "Yes",
          "output": "Yes",
          "status": "caution",
          "value": "25",
          "selectable": true,
          "warning": "USB-JTAG D+ pin by default. Use as GPIO only when USB-JTAG is not required."
        },
        {
          "id": "GPIO26",
          "input": "Yes",
          "output": "Yes",
          "status": "safe",
          "value": "26",
          "selectable": true,
          "note": "General-purpose GPIO. Verify board-level peripherals before assignment."
        },
        {
          "id": "GPIO27",
          "input": "Yes",
          "output": "Yes",
          "status": "safe",
          "value": "27",
          "selectable": true,
          "note": "General-purpose GPIO. Verify board-level peripherals before assignment."
        },
        {
          "id": "GPIO28",
          "input": "Yes",
          "output": "Yes",
          "status": "safe",
          "value": "28",
          "selectable": true,
          "note": "General-purpose GPIO. Verify board-level peripherals before assignment."
        },
        {
          "id": "GPIO29",
          "input": "Yes",
          "output": "Yes",
          "status": "safe",
          "value": "29",
          "selectable": true,
          "note": "General-purpose GPIO. Verify board-level peripherals before assignment."
        },
        {
          "id": "GPIO30",
          "input": "Yes",
          "output": "Yes",
          "status": "safe",
          "value": "30",
          "selectable": true,
          "note": "General-purpose GPIO. Verify board-level peripherals before assignment."
        },
        {
          "id": "GPIO31",
          "input": "Yes",
          "output": "Yes",
          "status": "safe",
          "value": "31",
          "selectable": true,
          "note": "General-purpose GPIO. Verify board-level peripherals before assignment."
        },
        {
          "id": "GPIO32",
          "input": "Yes",
          "output": "Yes",
          "status": "safe",
          "value": "32",
          "selectable": true,
          "note": "General-purpose GPIO. Verify board-level peripherals before assignment."
        },
        {
          "id": "GPIO33",
          "input": "Yes",
          "output": "Yes",
          "status": "safe",
          "value": "33",
          "selectable": true,
          "note": "General-purpose GPIO. Verify board-level peripherals before assignment."
        },
        {
          "id": "GPIO34",
          "input": "Yes",
          "output": "Yes",
          "status": "caution",
          "value": "34",
          "selectable": true,
          "warning": "Strapping pin sampled during reset. Ensure attached circuitry does not force an invalid boot level."
        },
        {
          "id": "GPIO35",
          "input": "Yes",
          "output": "Yes",
          "status": "caution",
          "value": "35",
          "selectable": true,
          "warning": "Strapping pin sampled during reset. Ensure attached circuitry does not force an invalid boot level."
        },
        {
          "id": "GPIO36",
          "input": "Yes",
          "output": "Yes",
          "status": "caution",
          "value": "36",
          "selectable": true,
          "warning": "Strapping pin sampled during reset. Ensure attached circuitry does not force an invalid boot level."
        },
        {
          "id": "GPIO37",
          "input": "Yes",
          "output": "Yes",
          "status": "caution",
          "value": "37",
          "selectable": true,
          "warning": "Strapping pin sampled during reset. Ensure attached circuitry does not force an invalid boot level."
        },
        {
          "id": "GPIO38",
          "input": "Yes",
          "output": "Yes",
          "status": "caution",
          "value": "38",
          "selectable": true,
          "warning": "Strapping pin sampled during reset. Ensure attached circuitry does not force an invalid boot level."
        },
        {
          "id": "GPIO39",
          "input": "Yes",
          "output": "Yes",
          "status": "safe",
          "value": "39",
          "selectable": true,
          "note": "General-purpose GPIO. Verify board-level peripherals before assignment."
        },
        {
          "id": "GPIO40",
          "input": "Yes",
          "output": "Yes",
          "status": "safe",
          "value": "40",
          "selectable": true,
          "note": "General-purpose GPIO. Verify board-level peripherals before assignment."
        },
        {
          "id": "GPIO41",
          "input": "Yes",
          "output": "Yes",
          "status": "safe",
          "value": "41",
          "selectable": true,
          "note": "General-purpose GPIO. Verify board-level peripherals before assignment."
        },
        {
          "id": "GPIO42",
          "input": "Yes",
          "output": "Yes",
          "status": "safe",
          "value": "42",
          "selectable": true,
          "note": "General-purpose GPIO. Verify board-level peripherals before assignment."
        },
        {
          "id": "GPIO43",
          "input": "Yes",
          "output": "Yes",
          "status": "safe",
          "value": "43",
          "selectable": true,
          "note": "General-purpose GPIO. Verify board-level peripherals before assignment."
        },
        {
          "id": "GPIO44",
          "input": "Yes",
          "output": "Yes",
          "status": "safe",
          "value": "44",
          "selectable": true,
          "note": "General-purpose GPIO. Verify board-level peripherals before assignment."
        },
        {
          "id": "GPIO45",
          "input": "Yes",
          "output": "Yes",
          "status": "safe",
          "value": "45",
          "selectable": true,
          "note": "General-purpose GPIO. Verify board-level peripherals before assignment."
        },
        {
          "id": "GPIO46",
          "input": "Yes",
          "output": "Yes",
          "status": "safe",
          "value": "46",
          "selectable": true,
          "note": "General-purpose GPIO. Verify board-level peripherals before assignment."
        },
        {
          "id": "GPIO47",
          "input": "Yes",
          "output": "Yes",
          "status": "safe",
          "value": "47",
          "selectable": true,
          "note": "General-purpose GPIO. Verify board-level peripherals before assignment."
        },
        {
          "id": "48+",
          "input": "Yes",
          "output": "Yes",
          "status": "safe",
          "value": "48+",
          "selectable": true,
          "note": "General-purpose GPIO on high-pin-count packages. Refer to board/package pinout for actual availability."
        }
      ]
    }
  }
}