{
  "id": "display.rpi_dpi_rgb",
  "domain": "display",
  "platform": "rpi_dpi_rgb",
  "helpUrl": "https://esphome.io/components/display/rpi_dpi_rgb/",
  "extends": "base_display.json",
  "display_builder": true,
  "displayType": "color",
  "fields": [
    {
      "key": "dimensions",
      "type": "object",
      "required": true,
      "lvl": "simple",
      "fields": [
        {
          "key": "width",
          "type": "number",
          "required": true,
          "lvl": "simple",
          "default": 800
        },
        {
          "key": "height",
          "type": "number",
          "required": true,
          "lvl": "simple",
          "default": 480
        },
        {
          "key": "offset_width",
          "type": "number",
          "required": false,
          "lvl": "normal",
          "default": 0
        },
        {
          "key": "offset_height",
          "type": "number",
          "required": false,
          "lvl": "normal",
          "default": 0
        }
      ]
    },
    {
      "key": "data_pins",
      "type": "object",
      "required": true,
      "lvl": "simple",
      "fields": [
        {
          "key": "red",
          "type": "fixed_list",
          "required": true,
          "lvl": "simple",
          "length": 5,
          "labels": ["R0", "R1", "R2", "R3", "R4"],
          "item": {
            "type": "gpio",
            "placeholder": "GPIOXX"
          }
        },
        {
          "key": "green",
          "type": "fixed_list",
          "required": true,
          "lvl": "simple",
          "length": 6,
          "labels": ["G0", "G1", "G2", "G3", "G4", "G5"],
          "item": {
            "type": "gpio",
            "placeholder": "GPIOXX"
          }
        },
        {
          "key": "blue",
          "type": "fixed_list",
          "required": true,
          "lvl": "simple",
          "length": 5,
          "labels": ["B0", "B1", "B2", "B3", "B4"],
          "item": {
            "type": "gpio",
            "placeholder": "GPIOXX"
          }
        }
      ]
    },
    {
      "key": "de_pin",
      "type": "gpio",
      "required": true,
      "lvl": "simple",
      "placeholder": "GPIOXX"
    },
    {
      "key": "pclk_pin",
      "type": "gpio",
      "required": true,
      "lvl": "simple",
      "placeholder": "GPIOXX"
    },
    {
      "key": "hsync_pin",
      "type": "gpio",
      "required": true,
      "lvl": "simple",
      "placeholder": "GPIOXX"
    },
    {
      "key": "vsync_pin",
      "type": "gpio",
      "required": true,
      "lvl": "simple",
      "placeholder": "GPIOXX"
    },
    {
      "key": "enable_pin",
      "type": "gpio",
      "required": false,
      "lvl": "normal",
      "placeholder": "GPIOXX"
    },
    {
      "key": "reset_pin",
      "type": "gpio",
      "required": false,
      "lvl": "normal",
      "placeholder": "GPIOXX"
    },
    {
      "key": "hsync_pulse_width",
      "type": "number",
      "required": false,
      "lvl": "advanced",
      "placeholder": "10"
    },
    {
      "key": "hsync_front_porch",
      "type": "number",
      "required": false,
      "lvl": "advanced",
      "placeholder": "20"
    },
    {
      "key": "hsync_back_porch",
      "type": "number",
      "required": false,
      "lvl": "advanced",
      "placeholder": "20"
    },
    {
      "key": "vsync_pulse_width",
      "type": "number",
      "required": false,
      "lvl": "advanced",
      "placeholder": "10"
    },
    {
      "key": "vsync_front_porch",
      "type": "number",
      "required": false,
      "lvl": "advanced",
      "placeholder": "10"
    },
    {
      "key": "vsync_back_porch",
      "type": "number",
      "required": false,
      "lvl": "advanced",
      "placeholder": "10"
    },
    {
      "key": "color_order",
      "type": "select",
      "required": false,
      "lvl": "normal",
      "default": "bgr",
      "options": [
        "bgr",
        "rgb"
      ]
    },
    {
      "key": "pclk_frequency",
      "type": "text",
      "required": false,
      "lvl": "advanced",
      "placeholder": "16MHz"
    },
    {
      "key": "pclk_inverted",
      "type": "boolean",
      "required": false,
      "lvl": "advanced",
      "note": "ESPHome docs describe the default as true."
    },
    {
      "key": "invert_colors",
      "type": "boolean",
      "required": false,
      "lvl": "normal"
    },
    {
      "key": "rotation",
      "type": "select",
      "required": false,
      "lvl": "normal",
      "default": "0",
      "options": [
        "0",
        "90",
        "180",
        "270"
      ]
    },
    {
      "key": "auto_clear_enabled",
      "type": "boolean",
      "required": false,
      "lvl": "normal"
    },
    {
      "key": "pages",
      "type": "yaml",
      "required": false,
      "lvl": "advanced"
    },
    {
      "key": "update_interval",
      "type": "duration",
      "required": false,
      "lvl": "normal",
      "default": "5s"
    }
  ]
}
